silkworm/__init__.py
silkworm/silktime/__init__.py
silkworm/silktime/cycle_timer.py
silkworm/silktime/tasking.py
silkworm/silktime/timer.py
silkworm/silktime/units.py
silkworm-0.0.2.1.dist-info/LICENSE
silkworm-0.0.2.1.dist-info/METADATA
silkworm-0.0.2.1.dist-info/WHEEL
silkworm-0.0.2.1.dist-info/top_level.txt
silkworm-0.0.2.1.dist-info/RECORD
